django_vueformgenerator/__init__.py
django_vueformgenerator/components.py
django_vueformgenerator/fields.py
django_vueformgenerator/schema.py
django_vueformgenerator/urls.py
django_vueformgenerator/views.py
django_vueformgenerator/static/css/django_vueformgenerator.css
django_vueformgenerator/static/js/django_vueformgenerator.js
django_vueformgenerator/templates/django_vueformgenerator/base.html
django_vueformgenerator-0.2.3.dist-info/DESCRIPTION.rst
django_vueformgenerator-0.2.3.dist-info/METADATA
django_vueformgenerator-0.2.3.dist-info/RECORD
django_vueformgenerator-0.2.3.dist-info/WHEEL
django_vueformgenerator-0.2.3.dist-info/metadata.json
django_vueformgenerator-0.2.3.dist-info/top_level.txt
