Metadata-Version: 2.0
Name: django-vueformgenerator
Version: 0.2.3
Summary: A package to help bridge the gap between Django's Forms and VueFormGenerator's Schemas using DjangoRestFramework.
Home-page: https://github.com/player1537/django-vueformgenerator
Author: Tanner Hobson
Author-email: thobson125@gmail.com
License: MIT
Keywords: django-vueformgenerator
Platform: UNKNOWN
Classifier: Development Status :: 3 - Alpha
Classifier: Framework :: Django
Classifier: Framework :: Django :: 1.8
Classifier: Framework :: Django :: 1.9
Classifier: Framework :: Django :: 1.10
Classifier: Intended Audience :: Developers
Classifier: License :: OSI Approved :: BSD License
Classifier: Natural Language :: English
Classifier: Programming Language :: Python :: 2
Classifier: Programming Language :: Python :: 2.7
Classifier: Programming Language :: Python :: 3
Classifier: Programming Language :: Python :: 3.2
Classifier: Programming Language :: Python :: 3.3
Classifier: Programming Language :: Python :: 3.4
Classifier: Programming Language :: Python :: 3.5
